pyexplorer/__init__.py
pyexplorer/cli.py
pyexplorer/package_explorer.py
pyexplorer/script_analyzer.py
pycode_explorer-0.1.0.dist-info/METADATA
pycode_explorer-0.1.0.dist-info/WHEEL
pycode_explorer-0.1.0.dist-info/entry_points.txt
pycode_explorer-0.1.0.dist-info/top_level.txt
pycode_explorer-0.1.0.dist-info/RECORD
